LICENSE
README.md
setup.py
dumbot/__init__.py
dumbot.egg-info/PKG-INFO
dumbot.egg-info/SOURCES.txt
dumbot.egg-info/dependency_links.txt
dumbot.egg-info/top_level.txt