Metadata-Version: 2.1
Name: dumbot
Version: 1.5.6
Summary: dumb async telegram bot for python 3
Author: Lonami Exo
Author-email: totufals@hotmail.com
Keywords: telegram,async,asyncio,bot
Classifier: Development Status :: 5 - Production/Stable
Classifier: Framework :: AsyncIO
Classifier: Intended Audience :: Developers
Classifier: License :: OSI Approved :: MIT License
Classifier: Programming Language :: Python :: 3
Classifier: Topic :: Communications :: Chat
License-File: LICENSE
